aveytense/__init__.py
aveytense/constants.py
aveytense/exceptions.py
aveytense/extensions.py
aveytense/operators.py
aveytense/py.typed
aveytense/util.py
aveytense/_collection/__init__.py
aveytense/_collection/_abroad.py
aveytense/_collection/_console.py
aveytense/_collection/_constants.py
aveytense/_collection/_exceptions.py
aveytense/_collection/_extensions.py
aveytense/_collection/_primal.py
aveytense/_collection/_util.py
aveytense/_collection/_version.py
aveytense-0.3.64.dist-info/METADATA
aveytense-0.3.64.dist-info/WHEEL
aveytense-0.3.64.dist-info/entry_points.txt
aveytense-0.3.64.dist-info/top_level.txt
aveytense-0.3.64.dist-info/RECORD
