Metadata-Version: 2.4
Name: aveytense
Version: 0.3.64
Summary: Library written in Python, includes several extensions for inbuilt Python solutions
Author: Aveyzan
Author-email: aveyzan@gmail.com
License: MIT
Project-URL: Documentation, https://aveyzan.xyz/aveytense/
Project-URL: Repository, https://github.com/Aveyzan/aveytense
Project-URL: Changes, https://docs.google.com/document/d/1GC_KAOXML65jNfBZA8GhVViqPnrMoFtbLv_jHvUhBlg/edit?usp=sharing
Project-URL: Issues, https://github.com/Aveyzan/aveytense/issues/
Project-URL: Donate, https://ko-fi.com/aveyzan
Keywords: annotations,backport,extensions,math,types,typing,utility
Classifier: Development Status :: 4 - Beta
Classifier: Intended Audience :: Developers
Classifier: Operating System :: OS Independent
Classifier: Programming Language :: Python :: 3
Classifier: Programming Language :: Python :: 3 :: Only
Classifier: Programming Language :: Python :: 3.8
Classifier: Programming Language :: Python :: 3.9
Classifier: Programming Language :: Python :: 3.10
Classifier: Programming Language :: Python :: 3.11
Classifier: Programming Language :: Python :: 3.12
Classifier: Programming Language :: Python :: 3.13
Classifier: Programming Language :: Python :: 3.14
Classifier: Programming Language :: Python :: 3.15
Classifier: Topic :: Software Development
Requires-Python: >=3.8
Requires-Dist: typing_extensions>=4.10.0
Dynamic: author
Dynamic: author-email
Dynamic: classifier
Dynamic: description
Dynamic: description-content-type
Dynamic: keywords
Dynamic: license
Dynamic: project-url
Dynamic: requires-dist
Dynamic: requires-python
Dynamic: summary
